{
  "build_list": [
    {
      "name": "Legion - Gold - Fabrication Flyer",
      "to_build": "LegionAirBasicFabber",
      "instance_count": 1,
      "max_num_assisters": 10,
      "priority": 100,
      "builders": [
        "LegionFactoryBasicAir"
      ],
      "build_conditions": [
        [
          {
            "test_type": "HasPersonalityTag",
            "string0": "gold",
            "boolean": true
          },
          {
            "test_type": "BaseThreatened",
            "boolean": false
          },
          {
            "test_type": "UnitCountOnPlanet",
            "unit_type_string0": "Fabber & Basic - Orbital",
            "compare0": "<",
            "value0": 2
          }
        ],
        [
          {
            "test_type": "HasPersonalityTag",
            "string0": "gold",
            "boolean": true
          },
          {
            "test_type": "BaseThreatened",
            "boolean": false
          },
          {
            "test_type": "NoWhereToRun",
            "boolean": false
          },
          {
            "test_type": "UnitCountOnPlanet",
            "unit_type_string0": "Orbital & Transport",
            "compare0": ">=",
            "value0": 1
          },
          {
            "test_type": "UnitCountOnPlanet",
            "unit_type_string0": "Fabber - Naval",
            "compare0": "<",
            "value0": 1
          }
        ],
        [
          {
            "test_type": "HasPersonalityTag",
            "string0": "gold",
            "boolean": true
          },
          {
            "test_type": "BaseThreatened",
            "boolean": false
          },
          {
            "test_type": "CanAffordPotentialDrain",
            "string0": "LegionAirBasicFabber"
          },
          {
            "test_type": "UnitRatioOnPlanet",
            "unit_type_string0": "Fabber & Basic & Air",
            "unit_type_string1": "Factory & Basic & Air",
            "compare0": "<",
            "value0": 0.5
          }
        ],
        [
          {
            "test_type": "HasPersonalityTag",
            "string0": "gold",
            "boolean": true
          },
          {
            "test_type": "BaseThreatened",
            "boolean": false
          },
          {
            "test_type": "AloneOnPlanet",
            "boolean": true
          },
          {
            "test_type": "CanAffordPotentialDrain",
            "string0": "LegionAirBasicFabber"
          },
          {
            "test_type": "UnitRatioOnPlanet",
            "unit_type_string0": "Fabber & Basic & Air",
            "unit_type_string1": "Factory & Basic & Air",
            "compare0": "<",
            "value0": 1.5
          }
        ]
      ]
    },
    {
      "name": "Legion - Gold - Raider - Scout",
      "to_build": "LegionAirBasicGunship",
      "instance_count": -1,
      "max_num_assisters": 10,
      "priority": 98,
      "builders": [
        "LegionFactoryBasicAir"
      ],
      "build_conditions": [
        [
          {
            "test_type": "HasPersonalityTag",
            "string0": "gold",
            "boolean": true
          },
          {
            "test_type": "BaseThreatened",
            "boolean": false
          },
          {
            "test_type": "HaveFullPlanetIntel",
            "boolean": false
          },
          {
            "test_type": "UnitCountPerPlanetRadius",
            "unit_type_string0": "Scout",
            "compare0": "<",
            "value0": 400
          },
          {
            "test_type": "UnitCountOnPlanet",
            "unit_type_string0": "Air & Scout",
            "compare0": "<",
            "value0": 1
          }
        ]
      ]
    },
    {
      "name": "Legion - Gold - Raider - Fight",
      "to_build": "LegionAirBasicGunship",
      "instance_count": -1,
      "max_num_assisters": 10,
      "priority": 96,
      "builders": [
        "LegionFactoryBasicAir"
      ],
      "build_conditions": [
        [
          {
            "test_type": "HasPersonalityTag",
            "string0": "gold",
            "boolean": true
          },
          {
            "test_type": "EnemySurfacePresenceOnPlanet",
            "boolean": true
          },
          {
            "test_type": "PlanetHighestEnemyArmyThreatRatio",
            "string0": "Air",
            "string1": "AntiAir",
            "compare0": "<",
            "value0": 0.9
          },
          {
            "test_type": "PlanetHighestEnemyArmyThreatRatio",
            "string0": "Air",
            "string1": "Air",
            "compare0": "<",
            "value0": 0.9
          },
          {
            "test_type": "UnitCountOnPlanet",
            "unit_type_string0": "Air & Bomber & Custom1 - Titan",
            "compare0": "==",
            "value0": 0
          }
        ]
      ]
    },
    {
      "name": "Legion - Gold - Stinger",
      "to_build": "LegionAirBasicBomb",
      "instance_count": -1,
      "max_num_assisters": 10,
      "priority": 96,
      "builders": [
        "LegionFactoryBasicAir"
      ],
      "build_conditions": [
        [
          {
            "test_type": "HasPersonalityTag",
            "string0": "gold",
            "boolean": true
          },
          {
            "test_type": "EnemyAirPresenceOnPlanet",
            "boolean": true
          },
          {
            "test_type": "PlanetHighestEnemyArmyThreatRatio",
            "string0": "Air",
            "string1": "AntiAir",
            "compare0": ">",
            "value0": 0.5
          }
        ],
        [
          {
            "test_type": "HasPersonalityTag",
            "string0": "gold",
            "boolean": true
          },
          {
            "test_type": "EnemyAirPresenceOnPlanet",
            "boolean": true
          },
          {
            "test_type": "PlanetHighestEnemyArmyThreatRatio",
            "string0": "Air",
            "string1": "Air",
            "compare0": ">",
            "value0": 0.5
          }
        ]
      ]
    },
    {
      "name": "Legion - Gold - Beamer",
      "to_build": "LegionAirBasicFighter",
      "instance_count": -1,
      "max_num_assisters": 10,
      "priority": 96,
      "builders": [
        "LegionFactoryBasicAir"
      ],
      "build_conditions": [
        [
          {
            "test_type": "HasPersonalityTag",
            "string0": "gold",
            "boolean": true
          },
          {
            "test_type": "AloneOnPlanet",
            "boolean": false
          },
          {
            "test_type": "EnemySurfacePresenceOnPlanet",
            "boolean": false
          },
          {
            "test_type": "EnemyAirPresenceOnPlanet",
            "boolean": false
          },
          {
            "test_type": "EnemyOrbitalPresenceOnPlanet",
            "boolean": false
          }
        ],
        [
          {
            "test_type": "HasPersonalityTag",
            "string0": "gold",
            "boolean": true
          },
          {
            "test_type": "EnemyAirPresenceOnPlanet",
            "boolean": true
          },
          {
            "test_type": "PlanetHighestEnemyArmyThreatRatio",
            "string0": "Air",
            "string1": "AntiAir",
            "compare0": ">",
            "value0": 0.5
          }
        ],
        [
          {
            "test_type": "HasPersonalityTag",
            "string0": "gold",
            "boolean": true
          },
          {
            "test_type": "EnemyAirPresenceOnPlanet",
            "boolean": true
          },
          {
            "test_type": "PlanetHighestEnemyArmyThreatRatio",
            "string0": "Air",
            "string1": "Air",
            "compare0": ">",
            "value0": 0.5
          }
        ]
      ]
    },
    {
      "name": "Legion - Gold - Dauntless",
      "to_build": "LegionAirBasicBomber",
      "instance_count": -1,
      "max_num_assisters": 10,
      "priority": 96,
      "builders": [
        "LegionFactoryBasicAir",
				"LegionFactoryAdvancedAir"
      ],
      "build_conditions": [
         [
          {
            "test_type": "HasPersonalityTag",
            "string0": "gold",
            "boolean": true
          },
          {
            "test_type": "AloneOnPlanet",
            "boolean": false
          },
          {
            "test_type": "EnemySurfacePresenceOnPlanet",
            "boolean": false
          },
          {
            "test_type": "EnemyAirPresenceOnPlanet",
            "boolean": false
          },
          {
            "test_type": "EnemyOrbitalPresenceOnPlanet",
            "boolean": false
          }
        ],
        [
          {
            "test_type": "HasPersonalityTag",
            "string0": "gold",
            "boolean": true
          },
          {
            "test_type": "EnemySurfacePresenceOnPlanet",
            "boolean": true
          },
          {
            "test_type": "PlanetHighestEnemyArmyThreatRatio",
            "string0": "Air",
            "string1": "AntiAir",
            "compare0": "<",
            "value0": 0.9
          },
          {
            "test_type": "PlanetHighestEnemyArmyThreatRatio",
            "string0": "Air",
            "string1": "Air",
            "compare0": "<",
            "value0": 0.9
          },
          {
            "test_type": "UnitCountOnPlanet",
            "unit_type_string0": "Air & Gunship & Custom1",
            "compare0": "==",
            "value0": 0
          }
        ]
      ]
    },
    {
      "name": "Legion - Gold - Advanced Fabrication Flyer",
      "to_build": "LegionAirAdvancedFabber",
      "instance_count": 1,
      "max_num_assisters": 10,
      "priority": 200,
      "builders": [
        "LegionFactoryAdvancedAir"
      ],
      "build_conditions": [
        [
          {
            "test_type": "HasPersonalityTag",
            "string0": "gold",
            "boolean": true
          },
          {
            "test_type": "BaseThreatened",
            "boolean": false
          },
          {
            "test_type": "UnitCountOnPlanet",
            "unit_type_string0": "Fabber & Advanced",
            "compare0": "<",
            "value0": 1
          }
        ],
        [
          {
            "test_type": "HasPersonalityTag",
            "string0": "gold",
            "boolean": true
          },
          {
            "test_type": "BaseThreatened",
            "boolean": false
          },
          {
            "test_type": "AloneOnPlanet",
            "boolean": false
          },
          {
            "test_type": "CanAffordPotentialDrain",
            "string0": "LegionAirAdvancedFabber"
          },
          {
            "test_type": "UnitRatioOnPlanet",
            "unit_type_string0": "Fabber & Advanced & Air",
            "unit_type_string1": "Factory & Advanced & Air",
            "compare0": "<",
            "value0": 1
          }
        ],
        [
          {
            "test_type": "HasPersonalityTag",
            "string0": "gold",
            "boolean": true
          },
          {
            "test_type": "BaseThreatened",
            "boolean": false
          },
          {
            "test_type": "AloneOnPlanet",
            "boolean": true
          },
          {
            "test_type": "CanAffordPotentialDrain",
            "string0": "LegionAirAdvancedFabber"
          },
          {
            "test_type": "UnitRatioOnPlanet",
            "unit_type_string0": "Fabber & Advanced & Air",
            "unit_type_string1": "Factory & Advanced & Air",
            "compare0": "<",
            "value0": 2
          }
        ]
      ]
    },
    {
      "name": "Legion - Gold - Stalker",
      "to_build": "LegionAirAdvancedScout",
      "instance_count": 1,
      "max_num_assisters": 10,
      "priority": 199,
      "builders": [
        "AnyLegionAirFactory"
      ],
      "build_conditions": [
         [
          {
            "test_type": "HasPersonalityTag",
            "string0": "gold",
            "boolean": true
          },
          {
            "test_type": "AloneOnPlanet",
            "boolean": false
          },
          {
            "test_type": "BaseThreatened",
            "boolean": false
          },
          {
            "test_type": "HaveFullPlanetIntel",
            "boolean": false
          },
          {
            "test_type": "UnitCountPerPlanetRadius",
            "unit_type_string0": "Scout",
            "compare0": "<",
            "value0": 400
          },
          {
            "test_type": "UnitCountOnPlanet",
            "unit_type_string0": "Air & Scout",
            "compare0": "<",
            "value0": 1
          }
        ]
      ]
    },
    {
      "name": "Legion - Gold - Firebird",
      "to_build": "LegionAirAdvancedFighter",
      "instance_count": -1,
      "max_num_assisters": 10,
      "priority": 198,
      "builders": [
        "LegionFactoryAdvancedAir"
      ],
      "build_conditions": [
        [
          {
            "test_type": "HasPersonalityTag",
            "string0": "gold",
            "boolean": true
          },
          {
            "test_type": "EnemyAirPresenceOnPlanet",
            "boolean": true
          },
          {
            "test_type": "PlanetHighestEnemyArmyThreatRatio",
            "string0": "Air",
            "string1": "AntiAir",
            "compare0": ">",
            "value0": 0.5
          }
        ],
        [
          {
            "test_type": "HasPersonalityTag",
            "string0": "gold",
            "boolean": true
          },
          {
            "test_type": "EnemyAirPresenceOnPlanet",
            "boolean": true
          },
          {
            "test_type": "PlanetHighestEnemyArmyThreatRatio",
            "string0": "Air",
            "string1": "Air",
            "compare0": ">",
            "value0": 0.5
          }
        ]
      ]
    },
    {
      "name": "Legion - Gold - Lockheed",
      "to_build": "LegionAirAdvancedGunship",
      "instance_count": -1,
      "max_num_assisters": 10,
      "priority": 198,
      "builders": [
        "LegionFactoryAdvancedAir"
      ],
      "build_conditions": [
        [
          {
            "test_type": "HasPersonalityTag",
            "string0": "gold",
            "boolean": true
          },
          {
            "test_type": "EnemySurfacePresenceOnPlanet",
            "boolean": true
          },
          {
            "test_type": "PlanetHighestEnemyArmyThreatRatio",
            "string0": "Air",
            "string1": "AntiAir",
            "compare0": "<",
            "value0": 0.9
          },
          {
            "test_type": "PlanetHighestEnemyArmyThreatRatio",
            "string0": "Air",
            "string1": "Air",
            "compare0": "<",
            "value0": 0.9
          },
          {
            "test_type": "UnitCountOnPlanet",
            "unit_type_string0": "Air & Bomber & Custom1 - Titan",
            "compare0": "==",
            "value0": 0
          }
        ]
      ]
    },
    {
      "name": "Legion - Gold - Purgatory",
      "to_build": "LegionAirAdvancedBomber",
      "instance_count": -1,
      "max_num_assisters": 10,
      "priority": 198,
      "builders": [
        "LegionFactoryAdvancedAir"
      ],
      "build_conditions": [
        [
          {
            "test_type": "HasPersonalityTag",
            "string0": "gold",
            "boolean": true
          },
          {
            "test_type": "EnemySurfacePresenceOnPlanet",
            "boolean": true
          },
          {
            "test_type": "PlanetHighestEnemyArmyThreatRatio",
            "string0": "Air",
            "string1": "AntiAir",
            "compare0": "<",
            "value0": 0.9
          },
          {
            "test_type": "PlanetHighestEnemyArmyThreatRatio",
            "string0": "Air",
            "string1": "Air",
            "compare0": "<",
            "value0": 0.9
          },
          {
            "test_type": "UnitCountOnPlanet",
            "unit_type_string0": "Air & Gunship & Custom1",
            "compare0": "==",
            "value0": 0
          }
        ]
      ]
    },
    {
      "name": "Legion - Gold - Comet",
      "to_build": "LegionAirAdvancedCarrier",
      "instance_count": 1,
      "max_num_assisters": 10,
      "priority": 198,
      "builders": [
        "LegionFactoryAdvancedAir"
      ],
      "build_conditions": [
        [
          {
            "test_type": "HasPersonalityTag",
            "string0": "gold",
            "boolean": true
          },
          {
            "test_type": "AloneOnPlanet",
            "boolean": false
          },
          {
            "test_type": "UnitRatioOnPlanet",
            "unit_type_string0": "Air & Mobile & (Offense | MissileDefense) - Fighter - Bomber - Gunship - SelfDestruct - Titan",
            "unit_type_string1": "Air & Mobile & (Offense | MissileDefense)",
            "compare0": "<",
            "value0": 0.05
          }
        ]
      ]
    }
  ]
}