{
  "build_list": [
    {
      "name": "Silver - Orbital Radar",
      "to_build": "Orbital_Radar",
      "instance_count": -1,
      "priority": 100,
      "build_conditions": [
        [
          {
            "test_type": "HasPersonalityTag",
            "string0": "silver",
            "boolean": true
          },
          {
            "test_type": "UnitPoolCount",
            "unit_type_string0": "Orbital & Recon - Structure",
            "compare0": ">=",
            "value0": 1
          },
          {
            "test_type": "UnitCountOnPlanet",
            "unit_type_string0": "Orbital & Structure & Economy",
            "compare0": "<",
            "value0": 1
          }
        ]
      ],
      "task_type": "OrbitalRecon"
    },
    {
      "name": "Silver - Orbital Radar Transfer To Planet",
      "to_build": "Orbital_Radar",
      "instance_count": 1,
      "priority": 101,
      "build_conditions": [
        [
          {
            "test_type": "HasPersonalityTag",
            "string0": "silver",
            "boolean": true
          },
          {
            "test_type": "OtherPlanetNeedsReconAssistance",
            "boolean": true
          },
          {
            "test_type": "UnitCountOnPlanet",
            "unit_type_string0": "Orbital & Recon - Structure",
            "compare0": ">",
            "value0": 1
          }
        ],
        [
          {
            "test_type": "HasPersonalityTag",
            "string0": "silver",
            "boolean": true
          },
          {
            "test_type": "PlanetIsGasGiant",
            "boolean": true
          },
          {
            "test_type": "OtherPlanetNeedsReconAssistance",
            "boolean": true
          }
        ],
        [
          {
            "test_type": "HasPersonalityTag",
            "string0": "silver",
            "boolean": true
          },
          {
            "test_type": "OtherPlanetNeedsReconAssistance",
            "boolean": true
          },
          {
            "test_type": "AloneOnPlanet",
            "boolean": true
          }
        ]
      ],
      "task_type": "TransferReconToPlanet"
    },
    {
      "name": "Silver - Orbital Fighter Attack Platoon",
      "to_build": "Orbital_Fighter_Attack",
      "instance_count": 2,
      "priority": 100,
      "build_conditions": [
        [
          {
            "test_type": "HasPersonalityTag",
            "string0": "silver",
            "boolean": true
          },
          {
            "test_type": "UnitPoolCount",
            "unit_type_string0": "Orbital & Fighter",
            "compare0": ">=",
            "value0": 10
          },
          {
            "test_type": "CanAttackWithPoolUnits"
          }
        ]
      ],
      "task_type": "OrbitalFighterAttack"
    },
    {
      "name": "Silver - Orbital Death Laser Attack Platoon",
      "to_build": "Orbital_Laser_Attack",
      "instance_count": -1,
      "priority": 100,
      "build_conditions": [
        [
          {
            "test_type": "HasPersonalityTag",
            "string0": "silver",
            "boolean": true
          },
          {
            "test_type": "UnitPoolCount",
            "unit_type_string0": "Orbital & LaserPlatform",
            "compare0": ">=",
            "value0": 1
          },
          {
            "test_type": "CanAttackWithPoolUnits"
          }
        ]
      ],
      "task_type": "OrbitalLaserAttack"
    }
  ]
}